instrukt/__init__.py
instrukt/_logging.py
instrukt/agent/__init__.py
instrukt/agent/base.py
instrukt/agent/builder.py
instrukt/agent/callback.py
instrukt/agent/events.py
instrukt/agent/loading.py
instrukt/agent/manager.py
instrukt/agent/memory.py
instrukt/agent/mrkl.py
instrukt/agent/state.py
instrukt/agent_modules/__init__.py
instrukt/agent_modules/chat_qa/__init__.py
instrukt/agent_modules/chat_qa/commands.py
instrukt/agent_modules/chat_qa/main.py
instrukt/agent_modules/chat_qa/manifest.json
instrukt/agent_modules/coding_ai/__init__.py
instrukt/agent_modules/coding_ai/main.py
instrukt/agent_modules/coding_ai/manifest.json
instrukt/agent_modules/coding_ai/prompt.py
instrukt/agent_modules/demo/__init__.py
instrukt/agent_modules/demo/commands.py
instrukt/agent_modules/demo/fake_conv.json
instrukt/agent_modules/demo/fake_conv.py
instrukt/agent_modules/demo/main.py
instrukt/agent_modules/demo/manifest.json
instrukt/app.py
instrukt/binding.py
instrukt/commands/__init__.py
instrukt/commands/agents.py
instrukt/commands/command.py
instrukt/commands/config.py
instrukt/commands/debug.py
instrukt/commands/help.py
instrukt/commands/history.py
instrukt/commands/index.py
instrukt/commands/root_cmd.py
instrukt/commands/ui.py
instrukt/config.py
instrukt/console_capture.py
instrukt/context.py
instrukt/docs/api.md
instrukt/docs/index.md
instrukt/docs/install.md
instrukt/docs/quickstart.md
instrukt/errors/__init__.py
instrukt/imgs/2023-06-14-214644_2032x1388_scrot.jpg
instrukt/indexes/__init__.py
instrukt/indexes/chroma.py
instrukt/indexes/embeddings.py
instrukt/indexes/instrukt_index.py
instrukt/indexes/loaders/__init__.py
instrukt/indexes/loaders/const.py
instrukt/indexes/loaders/dirloader.py
instrukt/indexes/loaders/mappings.py
instrukt/indexes/loaders/schema.py
instrukt/indexes/loaders/utils.py
instrukt/indexes/manager.py
instrukt/indexes/retrieval/__init__.py
instrukt/indexes/retrieval/qa_tool.py
instrukt/indexes/retrieval/utils.py
instrukt/indexes/schema.py
instrukt-0.6.3.dist-info/LICENSE
instrukt-0.6.3.dist-info/METADATA
instrukt-0.6.3.dist-info/WHEEL
instrukt-0.6.3.dist-info/entry_points.txt
instrukt-0.6.3.dist-info/RECORD
