Metadata-Version: 2.1
Name: instrukt
Version: 0.6.3
Summary: A versatile AI environment to build and control AI agents using a terminal-based interface.
Home-page: https://github.com/blob42/instrukt
License: AGPL3
Author: Chakib Benziane
Author-email: instrukt@blob42.xyz
Requires-Python: >=3.9,<4.0
Classifier: Development Status :: 3 - Alpha
Classifier: Environment :: Console
Classifier: Environment :: Web Environment
Classifier: Intended Audience :: Developers
Classifier: Intended Audience :: Science/Research
Classifier: License :: OSI Approved :: GNU Affero General Public License v3
Classifier: License :: Other/Proprietary License
Classifier: Operating System :: OS Independent
Classifier: Programming Language :: Python :: 3
Classifier: Programming Language :: Python :: 3.9
Classifier: Programming Language :: Python :: 3.10
Classifier: Programming Language :: Python :: 3.11
Classifier: Programming Language :: Python :: 3 :: Only
Classifier: Topic :: Scientific/Engineering :: Artificial Intelligence
Classifier: Topic :: Scientific/Engineering :: Human Machine Interfaces
Classifier: Topic :: Scientific/Engineering :: Information Analysis
Classifier: Topic :: Software Development :: Libraries :: Python Modules
Classifier: Topic :: Software Development :: User Interfaces
Classifier: Topic :: Text Processing :: Linguistic
Classifier: Topic :: Utilities
Provides-Extra: all
Provides-Extra: coding
Provides-Extra: local
Provides-Extra: openai
Provides-Extra: tools
Provides-Extra: torch
Requires-Dist: chardet (>=5.2.0,<6.0.0)
Requires-Dist: chromadb (>=0.4.8,<0.5.0)
Requires-Dist: esprima (>=4.0.1,<5.0.0) ; extra == "coding" or extra == "all"
Requires-Dist: instructorembedding (>=1.0.1,<2.0.0) ; extra == "local" or extra == "all"
Requires-Dist: ipython (>=8.13.2,<9.0.0)
Requires-Dist: langchain (==0.0.266)
Requires-Dist: nest-asyncio (>=1.5.6,<2.0.0)
Requires-Dist: openai (>=0.27.8,<0.28.0) ; extra == "openai" or extra == "all"
Requires-Dist: pdfminer-six (>=20221105,<20221106)
Requires-Dist: pydantic (>=1.10.7,<2.0.0)
Requires-Dist: pydantic-yaml (>=0.11.2,<0.12.0)
Requires-Dist: pyperclip (>=1.8.2,<2.0.0)
Requires-Dist: python-magic (>=0.4.27,<0.5.0)
Requires-Dist: pyxdg (>=0.28,<0.29)
Requires-Dist: pyyaml (>=6.0,<7.0)
Requires-Dist: rich (>=13.4.1,<14.0.0)
Requires-Dist: sentence-transformers (>=2.2.2,<3.0.0) ; extra == "local" or extra == "all"
Requires-Dist: textual (>=0.35.1,<0.36.0)
Requires-Dist: tiktoken (>=0.4.0,<0.5.0)
Requires-Dist: tomli (>=2.0.1,<3.0.0)
Requires-Dist: torch (==2.0.1) ; extra == "torch" or extra == "all"
Requires-Dist: typing-extensions (>=4.7.1,<5.0.0)
Requires-Dist: unstructured[local-inference] (>=0.6.11,<0.7.0)
Requires-Dist: wikipedia (>=1.4.0,<2.0.0) ; extra == "tools" or extra == "all"
Requires-Dist: wrapt (>=1.15.0,<2.0.0)
Project-URL: Documentation, https://github.com/blob42/instrukt/docs
Project-URL: Repository, https://github.com/blob42/instrukt
